processamento_imagem_pack/__init__.py
processamento_imagem_pack/processing/__init__.py
processamento_imagem_pack/processing/combination.py
processamento_imagem_pack/processing/transformation.py
processamento_imagem_pack/utils/__init__.py
processamento_imagem_pack/utils/io.py
processamento_imagem_pack/utils/plot.py
processamento_imagem_pack-0.0.1.dist-info/METADATA
processamento_imagem_pack-0.0.1.dist-info/WHEEL
processamento_imagem_pack-0.0.1.dist-info/top_level.txt
processamento_imagem_pack-0.0.1.dist-info/RECORD
