Metadata-Version: 2.1
Name: processamento_imagem_pack
Version: 0.0.1
Summary: Image Processing Package
Home-page: https://github.com/Ruukaas/image-processing-package
Author: Lucas Henrique
Author-email: lucashenriquehca@gmail.com
Requires-Python: >=3.8
Requires-Dist: scikit-image >=0.16.1
Requires-Dist: numpy
Requires-Dist: matplotlib
